{
  "id": "E060",
  "author": "Палехов Роман",
  "title": "Горсть зерна",
  "year": 1960,
  "nodes": [
    {
      "id": "sasha",
      "name": "Саша",
      "full_name": "Саша",
      "main": true,
      "who": "девушка, работающая на перевозке пшеницы",
      "aliases": "Саша, Сашка",
      "author_characterization": "влюбленная; ждущая; ревнивая",
      "gender": "женский",
      "age": "—",
      "other": "целый год не видела Николая"
    },
    {
      "id": "nikolai",
      "name": "Николай",
      "full_name": "Николай",
      "main": true,
      "who": "молодой шофер, возит пшеницу",
      "aliases": "Николай; Коля; Коленька",
      "author_characterization": "совсем молодой; добрый; избегает денежных разговоров",
      "gender": "мужской",
      "age": "молодой",
      "other": "позапрошлогодний десятиклассник"
    },
    {
      "id": "olga",
      "name": "Ольга",
      "full_name": "Ольга",
      "main": false,
      "who": "подруга Саши, ссыпщица",
      "aliases": "Ольга",
      "author_characterization": "худая; веснушчатая; завидует Саше",
      "gender": "женский",
      "age": "—",
      "other": "поет частушки"
    },
    {
      "id": "chernobrovaya_shoferikha",
      "name": "Чернобровая шофериха",
      "full_name": "Зоя",
      "main": false,
      "who": "женщина-шофер на другом грузовике",
      "aliases": "шофериха; чернобровая; цыганочка; Зоенька",
      "author_characterization": "чернобровая; черноглазая; круглолицая",
      "gender": "женский",
      "age": "молодая",
      "other": "Николай зовет ее Зоенькой"
    },
    {
      "id": "podrugi_ssypshchitsy",
      "name": "Подруги-ссыпщицы",
      "full_name": "—",
      "main": false,
      "who": "две другие подруги Саши на перевозке",
      "aliases": "две другие; подруги-ссыпщицы",
      "author_characterization": "радовались чужому счастью",
      "gender": "женский",
      "age": "—",
      "other": "едут в кузове с пшеницей"
    }
  ],
  "links": [
    {
      "source": "sasha",
      "target": "nikolai",
      "types": [
        "speech",
        "help_support",
        "transfer"
      ],
      "episode_count": 5,
      "weight": 1,
      "evidence": [
        "\"За три дня Николай с Сашей переговорил о многом\" - встреча после того, как Николай был год в отъезде",
        "разговор о чернобровой шоферихе",
        "разговор о том, почему Николай не остался в городе",
        "везет Сашу в кабине, обнимает, заботится о ней",
        "пересыпает последнюю горсть пшеницы ей в ладони"
      ],
      "notes": "встреча после долгой разлуки, разговоры, забота Николая о Саше и передача последней горсти пшеницы"
    },
    {
      "source": "sasha",
      "target": "olga",
      "types": [
        "co_presence_joint_action"
      ],
      "episode_count": 1,
      "weight": 0.1,
      "evidence": [
        "вместе едут и собирают рассыпанную пшеницу"
      ],
      "notes": "Саша и Ольга вместе едут и собирают рассыпанную пшеницу"
    },
    {
      "source": "olga",
      "target": "nikolai",
      "types": [
        "speech"
      ],
      "episode_count": 1,
      "weight": 0.3,
      "evidence": [
        "Ольга обращается к Николаю с насмешкой и замечанием"
      ],
      "notes": "Ольга насмешливо обращается к Николаю"
    },
    {
      "source": "olga",
      "target": "chernobrovaya_shoferikha",
      "types": [
        "speech"
      ],
      "episode_count": 1,
      "weight": 0.3,
      "evidence": [
        "Ольга прогоняет шофериху"
      ],
      "notes": "Ольга прогоняет чернобровую шофериху"
    },
    {
      "source": "nikolai",
      "target": "chernobrovaya_shoferikha",
      "types": [
        "speech",
        "conflict"
      ],
      "episode_count": 2,
      "weight": 0.5,
      "evidence": [
        "короткий обмен репликами после остановки",
        "раздражение и угроза из-за опасного соседства машин"
      ],
      "notes": "Николай коротко разговаривает с чернобровой шоферихой и раздражается из-за опасного соседства машин"
    },
    {
      "source": "sasha",
      "target": "chernobrovaya_shoferikha",
      "types": [
        "speech",
        "conflict"
      ],
      "episode_count": 2,
      "weight": 0.5,
      "evidence": [
        "Саша кричит шоферихе, чтобы та ехала вперед",
        "ревнивое соперничество между женщинами"
      ],
      "notes": "Саша кричит чернобровой шоферихе и ревнует ее к Николаю"
    },
    {
      "source": "sasha",
      "target": "podrugi_ssypshchitsy",
      "types": [
        "co_presence_joint_action"
      ],
      "episode_count": 1,
      "weight": 0.1,
      "evidence": [
        "вместе перевозят и собирают пшеницу"
      ],
      "notes": "Саша и подруги-ссыпщицы вместе перевозят и собирают пшеницу"
    },
    {
      "source": "nikolai",
      "target": "podrugi_ssypshchitsy",
      "types": [
        "co_presence_joint_action",
        "request"
      ],
      "episode_count": 2,
      "weight": 0.3,
      "evidence": [
        "вместе собирают рассыпанную пшеницу",
        "приказывает положить узел с зерном в угол и не высыпать"
      ],
      "notes": "Николай вместе с подругами-ссыпщицами собирает пшеницу и приказывает не высыпать узел с зерном"
    }
  ]
}