{
  "id": "S245",
  "author": "Зуев Александр Никанорович",
  "title": "Цена вещей",
  "year": 1928,
  "nodes": [
    {
      "id": "ivan_semyonovich",
      "name": "Иван Семёнович",
      "full_name": "—",
      "main": true,
      "who": "рассказчик, представитель Губпродкома по заготовкам",
      "aliases": "я; Иван Семёнович; представитель; старший по вагону",
      "author_characterization": "бережливый, скуповатый, самоуверенный, рассудительный о вещах",
      "gender": "мужской",
      "age": "средних лет",
      "other": "командирован из Губпродкома; едет в теплушке; становится старшим по вагону; ссорится с Лидией Михайловной из-за гребёнки"
    },
    {
      "id": "komendant",
      "name": "Комендант",
      "full_name": "—",
      "main": false,
      "who": "комендант, разрешивший Ивану Семёновичу сесть в теплушку",
      "aliases": "комендант",
      "author_characterization": "—",
      "gender": "мужской",
      "age": "—",
      "other": "направляет рассказчика в вагон на третьей линии"
    },
    {
      "id": "krasnoarmeytsy",
      "name": "Красноармейцы",
      "full_name": "—",
      "main": false,
      "who": "военные попутчики Ивана Семёновича",
      "aliases": "товарищи; человек десять; военные; ребята; красная армия моя; товарищи",
      "author_characterization": "народ служебный и не гордый",
      "gender": "мужской",
      "age": "—",
      "other": "устраиваются в теплушке, помогают сестрицам, поддерживают их при проверках"
    },
    {
      "id": "lidiya_mikhaylovna",
      "name": "Лидия Михайловна",
      "full_name": "Лидия Михайловна",
      "main": true,
      "who": "медицинская сестра, попутчица Ивана Семёновича",
      "aliases": "Лидия Михайловна; Лидия; Лидочка; прелестная сестрица; сестрица; дамочка; дитя",
      "author_characterization": "прехорошенькая; с синенькими глазами; ручка, как птичья лапка, сухонькая, маленькая",
      "gender": "женский",
      "age": "молодой",
      "other": "едет с запасами продуктов; сближается с Иваном Семёновичем; теряет его гребёнку и подвергается резкой брани"
    },
    {
      "id": "sestritsy",
      "name": "Сестрицы",
      "full_name": "—",
      "main": false,
      "who": "другие медицинские сестры, попутчицы Лидии Михайловны",
      "aliases": "сестрицы; сестрички; дамочки; четыре сестрицы",
      "author_characterization": "народ свойский, нестеснительные и вместе с тем веселые",
      "gender": "женский",
      "age": "молодой",
      "other": "едут с коробочками и запасами; вместе с Лидией Михайловной проходят проверки"
    },
    {
      "id": "zagradilovtsy",
      "name": "Заградиловцы",
      "full_name": "—",
      "main": false,
      "who": "проверяющие в поезде",
      "aliases": "заградиловцы; проверка; влезают с ружьями",
      "author_characterization": "—",
      "gender": "мужской",
      "age": "—",
      "other": "проверяют вагон и обыскивают сестриц, но ничего не отбирают"
    },
    {
      "id": "sestritsa_poslannitsa",
      "name": "Сестрица-посланница",
      "full_name": "—",
      "main": false,
      "who": "одна из сестриц, зовущая Ивана Семёновича к Лидии Михайловне на вокзале",
      "aliases": "одна из этих сестричек; сестричка",
      "author_characterization": "сама не своя",
      "gender": "женский",
      "age": "молодой",
      "other": "передает просьбу Лидии Михайловны увидеть Ивана Семёновича"
    }
  ],
  "links": [
    {
      "source": "komendant",
      "target": "ivan_semyonovich",
      "types": [
        "speech"
      ],
      "episode_count": 1,
      "intensity": 3,
      "weight": 0.11,
      "evidence": [
        "«Садись, – говорит, – в любую на третьей линии»"
      ],
      "notes": "комендант отвечает Ивану Семёновичу и разрешает сесть в любую теплушку"
    },
    {
      "source": "ivan_semyonovich",
      "target": "krasnoarmeytsy",
      "types": [
        "speech",
        "help_support",
        "request"
      ],
      "episode_count": 4,
      "intensity": 9,
      "weight": 0.33,
      "evidence": [
        "«А тут товарищей идёт человек десять. Я их и покликал всех.»",
        "«Печку-железку откуда-то сразу стащили, дров с паровоза нанесли и нары поправили.»",
        "«Теперь, ребята, уговор: никого без разбору сюда не пускать.»",
        "«Надо сестрицу пустить»",
        "«Тут велели выбрать старшего по вагону, и все показали на меня»"
      ],
      "notes": "Иван Семёнович зовет красноармейцев в свою теплушку; красноармейцы обустраивают теплушку после того, как Иван Семёнович уступает им место; Иван Семёнович договаривается с красноармейцами никого без разбора не пускать в вагон; Иван Семёнович убеждает красноармейцев пустить сестру в вагон; попутчики выбирают Ивана Семёновича старшим по вагону"
    },
    {
      "source": "ivan_semyonovich",
      "target": "lidiya_mikhaylovna",
      "types": [
        "request",
        "speech",
        "help_support",
        "co_presence_joint_action",
        "transfer",
        "conflict"
      ],
      "episode_count": 12,
      "intensity": 27,
      "weight": 1,
      "evidence": [
        "«„Пустите“, – говорит, а глаза так и молят.»",
        "«– А вы, о чем задумались?»",
        "«– Знаете, вполне возможно!»",
        "«У нас военный вагон, и я поговорю с комендантом.»",
        "«Больше всего я в мужчинах люблю характер твёрдый и положительность.»",
        "«как-то вышло, что я с Лидией Михайловной бок-в-бок»",
        "«Как бы спросонок закидываю я Лидию полой своего тулупа»",
        "«– Ах, как сладко я спала, совсем как дома!»",
        "«Гребенку она у меня перед этим взяла»",
        "«первый раз за всю дорогу высказал резкое слово»",
        "«Подайте именно ту!..»",
        "«Какая сейчас горькая цена вещам, не знаете?»"
      ],
      "notes": "Лидия Михайловна просит пустить ее в теплушку; Лидия Михайловна на платформе спрашивает Ивана Семёновича, о чем он задумался; Иван Семёнович разговаривает с Лидией Михайловной о возможном отборе вещей; Иван Семёнович успокаивает Лидию Михайловну и обещает поговорить с комендантом; Лидия Михайловна говорит Ивану Семёновичу, что ценит твердый характер; Иван Семёнович и Лидия Михайловна ночью лежат рядом на общих нарах; Иван Семёнович укрывает Лидию Михайловну полой тулупа; Лидия Михайловна утром говорит, что хорошо спала; Лидия Михайловна берет у Ивана Семёновича гребенку; Иван Семёнович резко ругает Лидию Михайловну после потери гребенки; Иван Семёнович требует у Лидии Михайловны вернуть именно потерянную гребенку; Иван Семёнович обвиняет Лидию Михайловну в непонимании цены вещей"
    },
    {
      "source": "lidiya_mikhaylovna",
      "target": "sestritsy",
      "types": [
        "co_presence_joint_action"
      ],
      "episode_count": 1,
      "intensity": 1,
      "weight": 0.1,
      "evidence": [
        "«Побежала она за коробочками и приводит неожиданно ещё четырёх сестриц»"
      ],
      "notes": "Лидия Михайловна приводит в вагон еще четырех сестриц"
    },
    {
      "source": "sestritsy",
      "target": "krasnoarmeytsy",
      "types": [
        "request",
        "help_support",
        "co_presence_joint_action"
      ],
      "episode_count": 4,
      "intensity": 7,
      "weight": 0.26,
      "evidence": [
        "«Одна попросила за водой сбегать»",
        "«так за чайничек чуть не драка, всякому охота подслужить»",
        "«И все друг другом очень довольны.»",
        "«И товарищи тоже под ряд загомонили: „чего, мол, военных сестриц обижать“»"
      ],
      "notes": "одна из сестриц просит красноармейцев сбегать за водой; красноармейцы охотно стараются услужить сестрицам; красноармейцы и сестрицы вместе едут в теплушке и довольны обществом друг друга; красноармейцы заступаются за сестриц перед заградиловцами"
    },
    {
      "source": "sestritsy",
      "target": "ivan_semyonovich",
      "types": [
        "speech",
        "help_support",
        "conflict"
      ],
      "episode_count": 3,
      "intensity": 7,
      "weight": 0.26,
      "evidence": [
        "«сестрицы мои все сводят разговор, – сколько чего можно провезти и где Кате бывают заградиловки»",
        "«Тут вынимаю я свой мандат на провоз и некоторый ихний запас выдаю, как за свой.»",
        "«Я всердцах, ни с кем не прощаясь, первый из вагона выскочил.»"
      ],
      "notes": "сестрицы расспрашивают о правилах провоза вещей и заградиловках; Иван Семёнович выдает часть запасов сестриц за свои по мандату; после ссоры с Лидией Михайловной Иван Семёнович уходит, ни с кем не прощаясь"
    },
    {
      "source": "zagradilovtsy",
      "target": "ivan_semyonovich",
      "types": [
        "speech"
      ],
      "episode_count": 1,
      "intensity": 3,
      "weight": 0.11,
      "evidence": [
        "«А тут как раз остановка и в дверь застучали. Я, как комендант, выхожу.»"
      ],
      "notes": "проверяющие стучат в вагон, и Иван Семёнович как старший выходит к ним"
    },
    {
      "source": "zagradilovtsy",
      "target": "sestritsy",
      "types": [
        "conflict",
        "co_presence_joint_action"
      ],
      "episode_count": 2,
      "intensity": 3,
      "weight": 0.11,
      "evidence": [
        "«А вот на сестричек-то насели, сестрички-то оказались с икрой.»",
        "«Так и ушли заградиловцы на радость нашим сестричкам, ничего не отобрали.»"
      ],
      "notes": "заградиловцы обыскивают сестриц и находят у них запасы; заградиловцы уходят, ничего не отобрав у сестриц"
    },
    {
      "source": "sestritsa_poslannitsa",
      "target": "ivan_semyonovich",
      "types": [
        "request",
        "speech"
      ],
      "episode_count": 2,
      "intensity": 5,
      "weight": 0.19,
      "evidence": [
        "«Лидочка очень хочет вас видеть, нужно ей что-то вам сказать. Очень просит!»",
        "«– Никак, – говорю, – оч-чего спешу. Будьте здоровы!»"
      ],
      "notes": "одна из сестриц передает Ивану Семёновичу просьбу Лидии Михайловны увидеться; Иван Семёнович отказывается идти к Лидии Михайловне"
    },
    {
      "source": "sestritsa_poslannitsa",
      "target": "lidiya_mikhaylovna",
      "types": [
        "transfer"
      ],
      "episode_count": 1,
      "intensity": 2,
      "weight": 0.1,
      "evidence": [
        "«Лидочка очень хочет вас видеть, нужно ей что-то вам сказать.»"
      ],
      "notes": "сестрица-посланница передает Ивану Семёновичу просьбу Лидии Михайловны"
    }
  ]
}